[
    {
        "id": "1",
        "label": "Home",
        "link": "/",
        "icon": false   
    },
    {
        "id": "2",
        "label": "Services",
        "link": "/service",
        "icon": true
        
    },
    {
        "id": "3",
        "label": "Case Study",
        "link": "/case-study",
        "icon": false
        
    },
    {
        "id": "5",
        "label": "About",
        "link": "/about-us",
        "icon": false
    },
    {
        "id": "6",
        "label": "Contact",
        "link": "/contact-us",
        "icon": false
    }
]